jes4py/Config.py
jes4py/FileChooser.py
jes4py/Picture.py
jes4py/PixelColor.py
jes4py/Sample.py
jes4py/Samples.py
jes4py/Sound.py
jes4py/SoundSample.py
jes4py/__init__.py
jes4py/media.py
jes4py/pictureTool.py
jes4py/show.py
jes4py_NickWestcoast-0.0.1.dist-info/LICENSE.txt
jes4py_NickWestcoast-0.0.1.dist-info/METADATA
jes4py_NickWestcoast-0.0.1.dist-info/WHEEL
jes4py_NickWestcoast-0.0.1.dist-info/top_level.txt
jes4py_NickWestcoast-0.0.1.dist-info/RECORD
