Metadata-Version: 2.1
Name: jes4py-NickWestcoast
Version: 0.0.1
Summary: A python package implementing part of JES's media functionality
Home-page: https://github.com/gordon-cs/JES-emulator
Author: Jonathan Senning
Author-email: jonathan.senning@gordon.edu
License: UNKNOWN
Platform: UNKNOWN
Classifier: Programming Language :: Python :: 3
Classifier: License :: OSI Approved :: MIT License
Classifier: Operating System :: OS Independent
Requires-Python: >=3.0.0
